LICENSE.txt
MANIFEST.in
README.rst
Target
logrotate.cfg
setup.py
chroma_agent/__init__.py
chroma_agent/agent_client.py
chroma_agent/agent_daemon.py
chroma_agent/cli.py
chroma_agent/config_store.py
chroma_agent/copytool_monitor.py
chroma_agent/crypto.py
chroma_agent/fence_chroma.py
chroma_agent/log.py
chroma_agent/plugin_manager.py
chroma_agent/scm_version.py
chroma_agent/utils.py
chroma_agent/action_plugins/__init__.py
chroma_agent/action_plugins/agent_setup.py
chroma_agent/action_plugins/agent_updates.py
chroma_agent/action_plugins/detect_scan.py
chroma_agent/action_plugins/device_plugin.py
chroma_agent/action_plugins/manage_client_mounts.py
chroma_agent/action_plugins/manage_conf_params.py
chroma_agent/action_plugins/manage_copytool.py
chroma_agent/action_plugins/manage_corosync.py
chroma_agent/action_plugins/manage_corosync2.py
chroma_agent/action_plugins/manage_corosync_common.py
chroma_agent/action_plugins/manage_fail_node.py
chroma_agent/action_plugins/manage_lnet.py
chroma_agent/action_plugins/manage_network.py
chroma_agent/action_plugins/manage_node.py
chroma_agent/action_plugins/manage_ntp.py
chroma_agent/action_plugins/manage_pacemaker.py
chroma_agent/action_plugins/manage_targets.py
chroma_agent/action_plugins/settings_management.py
chroma_agent/device_plugins/__init__.py
chroma_agent/device_plugins/action_runner.py
chroma_agent/device_plugins/block_devices.py
chroma_agent/device_plugins/corosync.py
chroma_agent/device_plugins/linux.py
chroma_agent/device_plugins/linux_network.py
chroma_agent/device_plugins/lustre.py
chroma_agent/device_plugins/systemd_journal.py
chroma_agent/device_plugins/audit/__init__.py
chroma_agent/device_plugins/audit/local.py
chroma_agent/device_plugins/audit/mixins.py
chroma_agent/device_plugins/audit/node.py
chroma_agent/device_plugins/audit/lustre/__init__.py
chroma_agent/lib/__init__.py
chroma_agent/lib/agent_startup_functions.py
chroma_agent/lib/agent_teardown_functions.py
chroma_agent/lib/corosync.py
iml_agent.egg-info/PKG-INFO
iml_agent.egg-info/SOURCES.txt
iml_agent.egg-info/dependency_links.txt
iml_agent.egg-info/entry_points.txt
iml_agent.egg-info/top_level.txt