Metadata-Version: 1.1
Name: iml-agent
Version: 4.1.1
Summary: The IML software Monitoring and Administration Interface Agent
Home-page: https://pypi.python.org/pypi/iml-agent
Author: Intel Corporation
Author-email: iml@intel.com
License: MIT
Keywords: IML lustre high-availability
Platform: UNKNOWN
Classifier: Development Status :: 5 - Production/Stable
Classifier: License :: OSI Approved :: MIT License
Classifier: Programming Language :: Python :: 2
Classifier: Programming Language :: Python :: 2.7
